{"inkVersion":19,"root":[[{"->":"knot0"},["done",{"#f":5,"#n":"g-0"}],null],"done",{"knot0":[{"->t->":"knotone"},"done",{"#f":1}],"knotone":[["ev","visit",4,"%","/ev","ev","du",0,"==","/ev",{"->":".^.s0","c":true},"ev","du",1,"==","/ev",{"->":".^.s1","c":true},"ev","du",2,"==","/ev",{"->":".^.s2","c":true},"ev","du",3,"==","/ev",{"->":".^.s3","c":true},"nop",{"s0":["pop",{"->":"knot1"},{"->":".^.^.29"},null],"s1":["pop","^ ",{"->":"knot2"},{"->":".^.^.29"},null],"s2":["pop","^ ",{"->":"knot3"},{"->":".^.^.29"},null],"s3":["pop","^ ",{"->":"knot4"},{"->":".^.^.29"},null],"#f":5}],"\n",{"#f":1}],"knot1":["^I hate the snow.","\n","^I hate december.","\n","^I hate being on winter break.","\n","ev","void","/ev","->->",{"#f":1}],"knot2":["^I wanna live in a rainy desert.","\n","ev","void","/ev","->->",{"#f":1}],"knot3":["^Every summer I wish it was winter.","\n","^Every winter I wish it was summer.","\n","^The weather's only really nice","\n","^for the first few days of the season.","\n","ev","void","/ev","->->",{"#f":1}],"knot4":["^I'd like to live in a space station.","\n","^like","\n","^a really cozy space station.","\n","^With a southwestern themed bar.","\n","ev","void","/ev","->->",{"#f":1}],"knot5":["^I don't have a favorite season.","\n","^They're all fine","\n","^when I feel okay","\n","^and then they're awful","\n","^when I feel awful.","\n","ev","void","/ev","->->",{"#f":1}],"#f":1}],"listDefs":{}}